totembionet.py
totembionet-10.dist-info/METADATA
totembionet-10.dist-info/RECORD
totembionet-10.dist-info/WHEEL
totembionet-10.dist-info/entry_points.txt
totembionet-10.dist-info/top_level.txt
